Metadata-Version: 2.1
Name: screeplot
Version: 0.0.1
Summary: Scree plot For Better Analyis the PCA
Home-page: UNKNOWN
Author-email: ranjitmaity95@gmail.com
License: UNKNOWN
Platform: UNKNOWN
